{
  "project_info": {
    "project_number": "849692686471",
    "project_id": "auth-f0c67",
    "storage_bucket": "auth-f0c67.firebasestorage.app"
  },
  "client": [
    {
      "client_info": {
        "mobilesdk_app_id": "1:849692686471:android:c8a7883ae507ae1c4f2022",
        "android_client_info": {
          "package_name": "com.example.flutter_auth"
        }
      },
      "oauth_client": [],
      "api_key": [
        {
          "current_key": "AIzaSyCHLFMJOlq379n8_5gDfSGmJIrKHd-z2Eo"
        }
      ],
      "services": {
        "appinvite_service": {
          "other_platform_oauth_client": []
        }
      }
    }
  ],
  "configuration_version": "1"
}